HISTORY.rst
LICENSE
MANIFEST.in
README.rst
setup.py
test_httpcache.py
test_requirements.txt
httpcache/__init__.py
httpcache/adapter.py
httpcache/cache.py
httpcache/compat.py
httpcache/structures.py
httpcache/utils.py
httpcache.egg-info/PKG-INFO
httpcache.egg-info/SOURCES.txt
httpcache.egg-info/dependency_links.txt
httpcache.egg-info/requires.txt
httpcache.egg-info/top_level.txt