Metadata-Version: 1.0
Name: httpcache
Version: 0.1.3
Summary: Simple HTTP cache for Python Requests
Home-page: http://httpcache.readthedocs.org/en/latest/
Author: Cory Benfield
Author-email: cory@lukasa.co.uk
License:    Copyright 2013 Cory Benfield
